LICENSE
MANIFEST.in
README.rst
setup.py
examples/simple_icmp.py
snortunsock/__init__.py
snortunsock/alert.py
snortunsock/snort_listener.py
snortunsock.egg-info/PKG-INFO
snortunsock.egg-info/SOURCES.txt
snortunsock.egg-info/dependency_links.txt
snortunsock.egg-info/not-zip-safe
snortunsock.egg-info/top_level.txt