Metadata-Version: 1.1
Name: snortunsock
Version: 0.0.5
Summary: A Python listener to capture Snort event via the UNIX Socket output
Home-page: https://github.com/John-Lin/snortunsock
Author: John Lin
Author-email: linton.tw@gmail.com
License: Apache License, Version 2.0
Platform: UNKNOWN
Classifier: Development Status :: 4 - Beta
Classifier: Environment :: Console
Classifier: Intended Audience :: Developers
Classifier: License :: OSI Approved :: Apache Software License
Classifier: Operating System :: OS Independent
Classifier: Programming Language :: Python
Classifier: Topic :: Utilities
Classifier: Topic :: Software Development :: Libraries :: Python Modules
Classifier: Programming Language :: Python :: 2.7
